<mxfile host="app.diagrams.net">
  <diagram id="C5RBs43oDa-KdzZeNtuy" name="Page-1">
    <mxGraphModel dx="1766" dy="1700" grid="1" gridSize="10" guides="1" tooltips="1" connect="1" arrows="1" fold="1" page="1" pageScale="1" pageWidth="827" pageHeight="1169" math="0" shadow="0">
      <root>
        <mxCell id="WIyWlLk6GJQsqaUBKTNV-0" />
        <mxCell id="WIyWlLk6GJQsqaUBKTNV-1" parent="WIyWlLk6GJQsqaUBKTNV-0" />
        <mxCell id="zkfFHV4jXpPFQw0GAbJ--0" parent="WIyWlLk6GJQsqaUBKTNV-1" style="swimlane;fontStyle=2;align=center;verticalAlign=top;childLayout=stackLayout;horizontal=1;startSize=26;horizontalStack=0;resizeParent=1;resizeLast=0;collapsible=1;marginBottom=0;rounded=0;shadow=0;strokeWidth=1;" value="Korisnik" vertex="1">
          <mxGeometry height="330" width="300" x="280" y="60" as="geometry">
            <mxRectangle height="26" width="160" x="230" y="140" as="alternateBounds" />
          </mxGeometry>
        </mxCell>
        <mxCell id="zkfFHV4jXpPFQw0GAbJ--1" parent="zkfFHV4jXpPFQw0GAbJ--0" style="text;align=left;verticalAlign=top;spacingLeft=4;spacingRight=4;overflow=hidden;rotatable=0;points=[[0,0.5],[1,0.5]];portConstraint=eastwest;" value="-id: int" vertex="1">
          <mxGeometry height="26" width="300" y="26" as="geometry" />
        </mxCell>
        <mxCell id="zkfFHV4jXpPFQw0GAbJ--2" parent="zkfFHV4jXpPFQw0GAbJ--0" style="text;align=left;verticalAlign=top;spacingLeft=4;spacingRight=4;overflow=hidden;rotatable=0;points=[[0,0.5],[1,0.5]];portConstraint=eastwest;rounded=0;shadow=0;html=0;" value="-imeIPrezime: string" vertex="1">
          <mxGeometry height="26" width="300" y="52" as="geometry" />
        </mxCell>
        <mxCell id="zkfFHV4jXpPFQw0GAbJ--3" parent="zkfFHV4jXpPFQw0GAbJ--0" style="text;align=left;verticalAlign=top;spacingLeft=4;spacingRight=4;overflow=hidden;rotatable=0;points=[[0,0.5],[1,0.5]];portConstraint=eastwest;rounded=0;shadow=0;html=0;" value="-email:  string" vertex="1">
          <mxGeometry height="26" width="300" y="78" as="geometry" />
        </mxCell>
        <mxCell id="1Qv8fr0okpyOL-LrenFo-0" parent="zkfFHV4jXpPFQw0GAbJ--0" style="text;align=left;verticalAlign=top;spacingLeft=4;spacingRight=4;overflow=hidden;rotatable=0;points=[[0,0.5],[1,0.5]];portConstraint=eastwest;rounded=0;shadow=0;html=0;" value="-lozinka: string" vertex="1">
          <mxGeometry height="26" width="300" y="104" as="geometry" />
        </mxCell>
        <mxCell id="1Qv8fr0okpyOL-LrenFo-11" parent="zkfFHV4jXpPFQw0GAbJ--0" style="text;align=left;verticalAlign=top;spacingLeft=4;spacingRight=4;overflow=hidden;rotatable=0;points=[[0,0.5],[1,0.5]];portConstraint=eastwest;rounded=0;shadow=0;html=0;" value="-uloga: enum" vertex="1">
          <mxGeometry height="26" width="300" y="130" as="geometry" />
        </mxCell>
        <mxCell id="QHBlkFtXS8DU_KKtdHjI-4" edge="1" parent="zkfFHV4jXpPFQw0GAbJ--0" source="QHBlkFtXS8DU_KKtdHjI-2" style="endArrow=none;html=1;rounded=0;exitX=0;exitY=0;exitDx=0;exitDy=0;entryX=1;entryY=0;entryDx=0;entryDy=0;" target="QHBlkFtXS8DU_KKtdHjI-2" value="">
          <mxGeometry height="50" relative="1" width="50" as="geometry">
            <mxPoint x="10" y="230" as="sourcePoint" />
            <mxPoint x="60" y="180" as="targetPoint" />
          </mxGeometry>
        </mxCell>
        <mxCell id="QHBlkFtXS8DU_KKtdHjI-2" parent="zkfFHV4jXpPFQw0GAbJ--0" style="text;html=1;whiteSpace=wrap;strokeColor=none;fillColor=none;align=left;verticalAlign=middle;rounded=0;" value="&lt;div&gt;&lt;br&gt;&lt;/div&gt;&lt;div&gt;+getImeIPrezime()&lt;/div&gt;&lt;div&gt;&lt;br&gt;&lt;/div&gt;&lt;div&gt;+setImeIPrezime(String ime)&lt;/div&gt;&lt;div&gt;&lt;br&gt;&lt;/div&gt;&lt;div&gt;&lt;span style=&quot;background-color: transparent; color: light-dark(rgb(0, 0, 0), rgb(255, 255, 255));&quot;&gt;+getEmail(), setEmail(String email)&lt;/span&gt;&lt;/div&gt;&lt;div&gt;&lt;span style=&quot;background-color: transparent; color: light-dark(rgb(0, 0, 0), rgb(255, 255, 255));&quot;&gt;&lt;br&gt;&lt;/span&gt;&lt;/div&gt;&lt;div&gt;+getUsername(), setUsername(String username)&lt;/div&gt;&lt;div&gt;&lt;br&gt;&lt;/div&gt;&lt;div&gt;+getUloga(), setUloga(enum uloga)&lt;/div&gt;&lt;div&gt;&lt;br&gt;&lt;/div&gt;&lt;div&gt;+provjeriLozinku(String lozinka) : bool&lt;/div&gt;" vertex="1">
          <mxGeometry height="164" width="300" y="156" as="geometry" />
        </mxCell>
        <mxCell id="zkfFHV4jXpPFQw0GAbJ--6" parent="WIyWlLk6GJQsqaUBKTNV-1" style="swimlane;fontStyle=0;align=center;verticalAlign=top;childLayout=stackLayout;horizontal=1;startSize=26;horizontalStack=0;resizeParent=1;resizeLast=0;collapsible=1;marginBottom=0;rounded=0;shadow=0;strokeWidth=1;" value="Student" vertex="1">
          <mxGeometry height="370" width="340" x="-170" y="-170" as="geometry">
            <mxRectangle height="26" width="160" x="130" y="380" as="alternateBounds" />
          </mxGeometry>
        </mxCell>
        <mxCell id="zkfFHV4jXpPFQw0GAbJ--10" parent="zkfFHV4jXpPFQw0GAbJ--6" style="text;align=left;verticalAlign=top;spacingLeft=4;spacingRight=4;overflow=hidden;rotatable=0;points=[[0,0.5],[1,0.5]];portConstraint=eastwest;fontStyle=4" value="-indeks: int" vertex="1">
          <mxGeometry height="26" width="340" y="26" as="geometry" />
        </mxCell>
        <mxCell id="1Qv8fr0okpyOL-LrenFo-19" parent="zkfFHV4jXpPFQw0GAbJ--6" style="text;align=left;verticalAlign=top;spacingLeft=4;spacingRight=4;overflow=hidden;rotatable=0;points=[[0,0.5],[1,0.5]];portConstraint=eastwest;rounded=0;shadow=0;html=0;" value="-prijavljeniIspiti: List&lt;PrijavaIspiti&gt;" vertex="1">
          <mxGeometry height="26" width="340" y="52" as="geometry" />
        </mxCell>
        <mxCell id="1Qv8fr0okpyOL-LrenFo-20" parent="zkfFHV4jXpPFQw0GAbJ--6" style="text;align=left;verticalAlign=top;spacingLeft=4;spacingRight=4;overflow=hidden;rotatable=0;points=[[0,0.5],[1,0.5]];portConstraint=eastwest;rounded=0;shadow=0;html=0;" value="-predaneZadace: List&lt;PredaneZadace&gt;" vertex="1">
          <mxGeometry height="26" width="340" y="78" as="geometry" />
        </mxCell>
        <mxCell id="QHBlkFtXS8DU_KKtdHjI-0" parent="zkfFHV4jXpPFQw0GAbJ--6" style="text;html=1;whiteSpace=wrap;strokeColor=none;fillColor=none;align=left;verticalAlign=middle;rounded=0;" value="&lt;div&gt;&amp;lt;&amp;lt;create&amp;gt;&amp;gt; +Student(indeks: int)&lt;/div&gt;&lt;div&gt;&lt;br&gt;&lt;/div&gt;&lt;div&gt;+dodajPrijavuIspita(PrijavaIspit prijava)&lt;/div&gt;&lt;div&gt;&lt;br&gt;&lt;/div&gt;&lt;div&gt;+dodajPredajuZadace(PredajaZadace predaja)&lt;/div&gt;&lt;div&gt;&lt;br&gt;&lt;/div&gt;&lt;div&gt;+pregledajPrijaveIspita() : List&amp;lt;PrijavaIspit&amp;gt;&lt;/div&gt;&lt;div&gt;&lt;br&gt;&lt;/div&gt;&lt;div&gt;+pregledajPredaneZadace() : List&amp;lt;PredajaZadace&amp;gt;&lt;/div&gt;&lt;div&gt;&lt;br&gt;&lt;/div&gt;&lt;div&gt;+posaljiZahtjevZaDokument(String tipDokumenta)&lt;/div&gt;&lt;div&gt;&lt;br&gt;&lt;/div&gt;&lt;div&gt;&lt;div&gt;+pregledOcjene()&lt;/div&gt;&lt;div&gt;&lt;br&gt;&lt;/div&gt;&lt;div&gt;+pregledBodova()&lt;/div&gt;&lt;div&gt;&lt;br&gt;&lt;/div&gt;&lt;div&gt;+pregledPrisustva()&lt;/div&gt;&lt;/div&gt;&lt;div&gt;&lt;br&gt;&lt;/div&gt;" vertex="1">
          <mxGeometry height="266" width="340" y="104" as="geometry" />
        </mxCell>
        <mxCell id="QHBlkFtXS8DU_KKtdHjI-1" edge="1" parent="zkfFHV4jXpPFQw0GAbJ--6" source="QHBlkFtXS8DU_KKtdHjI-0" style="endArrow=none;html=1;rounded=0;exitX=0;exitY=0;exitDx=0;exitDy=0;entryX=1;entryY=0;entryDx=0;entryDy=0;" target="QHBlkFtXS8DU_KKtdHjI-0" value="">
          <mxGeometry height="50" relative="1" width="50" as="geometry">
            <mxPoint x="210" y="110" as="sourcePoint" />
            <mxPoint x="260" y="60" as="targetPoint" />
          </mxGeometry>
        </mxCell>
        <mxCell id="zkfFHV4jXpPFQw0GAbJ--13" parent="WIyWlLk6GJQsqaUBKTNV-1" style="swimlane;fontStyle=1;align=center;verticalAlign=top;childLayout=stackLayout;horizontal=1;startSize=26;horizontalStack=0;resizeParent=1;resizeLast=0;collapsible=1;marginBottom=0;rounded=0;shadow=0;strokeWidth=1;" value="Profesor" vertex="1">
          <mxGeometry height="360" width="320" x="190" y="430" as="geometry">
            <mxRectangle height="26" width="170" x="340" y="380" as="alternateBounds" />
          </mxGeometry>
        </mxCell>
        <mxCell id="1Qv8fr0okpyOL-LrenFo-14" parent="zkfFHV4jXpPFQw0GAbJ--13" style="text;align=left;verticalAlign=top;spacingLeft=4;spacingRight=4;overflow=hidden;rotatable=0;points=[[0,0.5],[1,0.5]];portConstraint=eastwest;rounded=0;shadow=0;html=0;" value="-id: int " vertex="1">
          <mxGeometry height="26" width="320" y="26" as="geometry" />
        </mxCell>
        <mxCell id="1Qv8fr0okpyOL-LrenFo-16" parent="zkfFHV4jXpPFQw0GAbJ--13" style="text;align=left;verticalAlign=top;spacingLeft=4;spacingRight=4;overflow=hidden;rotatable=0;points=[[0,0.5],[1,0.5]];portConstraint=eastwest;rounded=0;shadow=0;html=0;" value="-titula: String" vertex="1">
          <mxGeometry height="26" width="320" y="52" as="geometry" />
        </mxCell>
        <mxCell id="1Qv8fr0okpyOL-LrenFo-17" parent="zkfFHV4jXpPFQw0GAbJ--13" style="text;align=left;verticalAlign=top;spacingLeft=4;spacingRight=4;overflow=hidden;rotatable=0;points=[[0,0.5],[1,0.5]];portConstraint=eastwest;rounded=0;shadow=0;html=0;" value="-predmetiNaKojimPredaje: List&lt;Predmeti&gt;" vertex="1">
          <mxGeometry height="26" width="320" y="78" as="geometry" />
        </mxCell>
        <mxCell id="1Qv8fr0okpyOL-LrenFo-18" parent="zkfFHV4jXpPFQw0GAbJ--13" style="text;align=left;verticalAlign=top;spacingLeft=4;spacingRight=4;overflow=hidden;rotatable=0;points=[[0,0.5],[1,0.5]];portConstraint=eastwest;rounded=0;shadow=0;html=0;" value="-dostupneZadace: List&lt;Zadaca&gt;" vertex="1">
          <mxGeometry height="26" width="320" y="104" as="geometry" />
        </mxCell>
        <mxCell id="QHBlkFtXS8DU_KKtdHjI-7" edge="1" parent="zkfFHV4jXpPFQw0GAbJ--13" source="QHBlkFtXS8DU_KKtdHjI-6" style="endArrow=none;html=1;rounded=0;exitX=0;exitY=0;exitDx=0;exitDy=0;entryX=1;entryY=0;entryDx=0;entryDy=0;" target="QHBlkFtXS8DU_KKtdHjI-6" value="">
          <mxGeometry height="50" relative="1" width="50" as="geometry">
            <mxPoint x="110" y="150" as="sourcePoint" />
            <mxPoint x="160" y="100" as="targetPoint" />
          </mxGeometry>
        </mxCell>
        <mxCell id="QHBlkFtXS8DU_KKtdHjI-6" parent="zkfFHV4jXpPFQw0GAbJ--13" style="text;html=1;whiteSpace=wrap;strokeColor=none;fillColor=none;align=left;verticalAlign=middle;rounded=0;" value="&lt;div&gt;&lt;br&gt;&lt;/div&gt;&lt;div&gt;&lt;br&gt;&lt;/div&gt;&lt;div&gt;&amp;lt;&amp;lt;create&amp;gt;&amp;gt; +Profesor(id: int, titula: String)&lt;/div&gt;&lt;div&gt;&lt;br&gt;&lt;/div&gt;&lt;div&gt;+dodajPredmet(Predmet predmet)&lt;/div&gt;&lt;div&gt;&lt;br&gt;&lt;/div&gt;&lt;div&gt;+dodajZadacu(Zadaca zadaca)&lt;/div&gt;&lt;div&gt;&lt;br&gt;&lt;/div&gt;&lt;div&gt;+pregledajPredmete() : List&amp;lt;Predmet&amp;gt;&lt;/div&gt;&lt;div&gt;&lt;br&gt;&lt;/div&gt;&lt;div&gt;+pregledajZadace() : List&amp;lt;Zadaca&amp;gt;&lt;/div&gt;&lt;div&gt;&lt;br&gt;&lt;/div&gt;&lt;div&gt;&lt;div&gt;+unesiBodovanje(PredajaZadace predaja, int bodovi)&lt;/div&gt;&lt;div&gt;&lt;br&gt;&lt;/div&gt;&lt;div&gt;+unesiOcjenu(Student student, Ispit ispit, int ocjena)&lt;/div&gt;&lt;div&gt;&lt;br&gt;&lt;/div&gt;&lt;div&gt;+unesiPrisustvo(Student student, Predmet predmet, boolean prisutan)&lt;/div&gt;&lt;/div&gt;" vertex="1">
          <mxGeometry height="200" width="320" y="130" as="geometry" />
        </mxCell>
        <mxCell id="1Qv8fr0okpyOL-LrenFo-2" edge="1" parent="WIyWlLk6GJQsqaUBKTNV-1" source="zkfFHV4jXpPFQw0GAbJ--10" style="endArrow=block;dashed=1;endFill=0;endSize=12;html=1;rounded=0;exitX=1;exitY=0.5;exitDx=0;exitDy=0;entryX=-0.012;entryY=0.089;entryDx=0;entryDy=0;entryPerimeter=0;" target="zkfFHV4jXpPFQw0GAbJ--0" value="">
          <mxGeometry relative="1" width="160" as="geometry">
            <Array as="points" />
            <mxPoint x="170" y="59" as="sourcePoint" />
            <mxPoint x="320" y="320" as="targetPoint" />
          </mxGeometry>
        </mxCell>
        <mxCell id="1Qv8fr0okpyOL-LrenFo-3" edge="1" parent="WIyWlLk6GJQsqaUBKTNV-1" source="zkfFHV4jXpPFQw0GAbJ--13" style="endArrow=block;dashed=1;endFill=0;endSize=12;html=1;rounded=0;exitX=0.5;exitY=0;exitDx=0;exitDy=0;entryX=0.5;entryY=1;entryDx=0;entryDy=0;" target="zkfFHV4jXpPFQw0GAbJ--0" value="">
          <mxGeometry relative="1" width="160" as="geometry">
            <mxPoint x="370" y="440" as="sourcePoint" />
            <mxPoint x="360" y="350" as="targetPoint" />
          </mxGeometry>
        </mxCell>
        <mxCell id="1Qv8fr0okpyOL-LrenFo-4" parent="WIyWlLk6GJQsqaUBKTNV-1" style="swimlane;fontStyle=0;align=center;verticalAlign=top;childLayout=stackLayout;horizontal=1;startSize=26;horizontalStack=0;resizeParent=1;resizeLast=0;collapsible=1;marginBottom=0;rounded=0;shadow=0;strokeWidth=1;" value="Administrator" vertex="1">
          <mxGeometry height="200" width="230" x="560" y="465" as="geometry">
            <mxRectangle height="26" width="170" x="340" y="380" as="alternateBounds" />
          </mxGeometry>
        </mxCell>
        <mxCell id="1Qv8fr0okpyOL-LrenFo-12" parent="1Qv8fr0okpyOL-LrenFo-4" style="text;align=left;verticalAlign=top;spacingLeft=4;spacingRight=4;overflow=hidden;rotatable=0;points=[[0,0.5],[1,0.5]];portConstraint=eastwest;rounded=0;shadow=0;html=0;" value="-lozinka: string" vertex="1">
          <mxGeometry height="26" width="230" y="26" as="geometry" />
        </mxCell>
        <mxCell id="kA5UPvO6djHCNP10DwQC-9" parent="1Qv8fr0okpyOL-LrenFo-4" style="text;align=left;verticalAlign=top;spacingLeft=4;spacingRight=4;overflow=hidden;rotatable=0;points=[[0,0.5],[1,0.5]];portConstraint=eastwest;rounded=0;shadow=0;html=0;" value="-zahtjevi: List&lt;AdminZahtjev&gt;" vertex="1">
          <mxGeometry height="26" width="230" y="52" as="geometry" />
        </mxCell>
        <mxCell id="QHBlkFtXS8DU_KKtdHjI-20" parent="1Qv8fr0okpyOL-LrenFo-4" style="text;html=1;whiteSpace=wrap;strokeColor=none;fillColor=none;align=left;verticalAlign=middle;rounded=0;" value="&lt;div&gt;&amp;lt;&amp;lt;create&amp;gt;&amp;gt; +Administrator(lozinka: String)&lt;/div&gt;&lt;div&gt;&lt;br&gt;&lt;/div&gt;&lt;div&gt;+dodajZahtjev(AdminZahtjev zahtjev)&lt;/div&gt;&lt;div&gt;&lt;br&gt;&lt;/div&gt;&lt;div&gt;+pregledajZahtjeve() : List&amp;lt;AdminZahtjev&amp;gt;&lt;/div&gt;&lt;div&gt;&lt;br&gt;&lt;/div&gt;&lt;div&gt;+obradiZahtjev(int idZahtjeva)&lt;/div&gt;" vertex="1">
          <mxGeometry height="120" width="230" y="78" as="geometry" />
        </mxCell>
        <mxCell id="QHBlkFtXS8DU_KKtdHjI-21" edge="1" parent="1Qv8fr0okpyOL-LrenFo-4" source="QHBlkFtXS8DU_KKtdHjI-20" style="endArrow=none;html=1;rounded=0;exitX=0;exitY=0;exitDx=0;exitDy=0;entryX=0.992;entryY=1.021;entryDx=0;entryDy=0;entryPerimeter=0;" target="kA5UPvO6djHCNP10DwQC-9" value="">
          <mxGeometry height="50" relative="1" width="50" as="geometry">
            <mxPoint x="170" y="80" as="sourcePoint" />
            <mxPoint x="220" y="30" as="targetPoint" />
          </mxGeometry>
        </mxCell>
        <mxCell id="1Qv8fr0okpyOL-LrenFo-7" edge="1" parent="WIyWlLk6GJQsqaUBKTNV-1" source="1Qv8fr0okpyOL-LrenFo-4" style="endArrow=block;dashed=1;endFill=0;endSize=12;html=1;rounded=0;exitX=0;exitY=0.25;exitDx=0;exitDy=0;entryX=1;entryY=1;entryDx=0;entryDy=0;" target="zkfFHV4jXpPFQw0GAbJ--0" value="">
          <mxGeometry relative="1" width="160" as="geometry">
            <mxPoint x="500" y="230" as="sourcePoint" />
            <mxPoint x="439" y="51" as="targetPoint" />
          </mxGeometry>
        </mxCell>
        <mxCell id="1Qv8fr0okpyOL-LrenFo-8" parent="WIyWlLk6GJQsqaUBKTNV-1" style="swimlane;fontStyle=0;align=center;verticalAlign=top;childLayout=stackLayout;horizontal=1;startSize=26;horizontalStack=0;resizeParent=1;resizeLast=0;collapsible=1;marginBottom=0;rounded=0;shadow=0;strokeWidth=1;" value="Studentska služba" vertex="1">
          <mxGeometry height="220" width="290" x="690" y="-81" as="geometry">
            <mxRectangle height="26" width="170" x="340" y="380" as="alternateBounds" />
          </mxGeometry>
        </mxCell>
        <mxCell id="1Qv8fr0okpyOL-LrenFo-22" parent="1Qv8fr0okpyOL-LrenFo-8" style="text;align=left;verticalAlign=top;spacingLeft=4;spacingRight=4;overflow=hidden;rotatable=0;points=[[0,0.5],[1,0.5]];portConstraint=eastwest;rounded=0;shadow=0;html=0;" value="-id: int" vertex="1">
          <mxGeometry height="26" width="290" y="26" as="geometry" />
        </mxCell>
        <mxCell id="kA5UPvO6djHCNP10DwQC-8" parent="1Qv8fr0okpyOL-LrenFo-8" style="text;align=left;verticalAlign=top;spacingLeft=4;spacingRight=4;overflow=hidden;rotatable=0;points=[[0,0.5],[1,0.5]];portConstraint=eastwest;rounded=0;shadow=0;html=0;" value="-zahtjevi: List&lt;ZahtjevZaDokument&gt;&#xa;" vertex="1">
          <mxGeometry height="26" width="290" y="52" as="geometry" />
        </mxCell>
        <mxCell id="QHBlkFtXS8DU_KKtdHjI-19" edge="1" parent="1Qv8fr0okpyOL-LrenFo-8" source="QHBlkFtXS8DU_KKtdHjI-18" style="endArrow=none;html=1;rounded=0;exitX=0;exitY=0;exitDx=0;exitDy=0;entryX=1;entryY=0;entryDx=0;entryDy=0;" target="QHBlkFtXS8DU_KKtdHjI-18" value="">
          <mxGeometry height="50" relative="1" width="50" as="geometry">
            <mxPoint x="40" y="291" as="sourcePoint" />
            <mxPoint x="90" y="241" as="targetPoint" />
          </mxGeometry>
        </mxCell>
        <mxCell id="QHBlkFtXS8DU_KKtdHjI-18" parent="1Qv8fr0okpyOL-LrenFo-8" style="text;html=1;whiteSpace=wrap;strokeColor=none;fillColor=none;align=left;verticalAlign=middle;rounded=0;" value="&lt;div&gt;&amp;lt;&amp;lt;create&amp;gt;&amp;gt; +StudentskaSluzba(id: int)&lt;/div&gt;&lt;div&gt;&lt;br&gt;&lt;/div&gt;&lt;div&gt;+dodajZahtjev(ZahtjevZaDokument zahtjev)&lt;/div&gt;&lt;div&gt;&lt;br&gt;&lt;/div&gt;&lt;div&gt;+pregledajZahtjeve() : List&amp;lt;ZahtjevZaDokument&amp;gt;&lt;/div&gt;&lt;div&gt;&lt;br&gt;&lt;/div&gt;&lt;div style=&quot;&quot;&gt;+obradiZahtjev(int idZahtjeva)&lt;/div&gt;" vertex="1">
          <mxGeometry height="130" width="290" y="78" as="geometry" />
        </mxCell>
        <mxCell id="1Qv8fr0okpyOL-LrenFo-10" edge="1" parent="WIyWlLk6GJQsqaUBKTNV-1" source="1Qv8fr0okpyOL-LrenFo-8" style="endArrow=block;dashed=1;endFill=0;endSize=12;html=1;rounded=0;entryX=1;entryY=0;entryDx=0;entryDy=0;exitX=0;exitY=0.5;exitDx=0;exitDy=0;" target="zkfFHV4jXpPFQw0GAbJ--0" value="">
          <mxGeometry relative="1" width="160" as="geometry">
            <mxPoint x="681" y="312" as="sourcePoint" />
            <mxPoint x="520" y="290" as="targetPoint" />
          </mxGeometry>
        </mxCell>
        <mxCell id="1Qv8fr0okpyOL-LrenFo-23" parent="WIyWlLk6GJQsqaUBKTNV-1" style="swimlane;fontStyle=0;align=center;verticalAlign=top;childLayout=stackLayout;horizontal=1;startSize=26;horizontalStack=0;resizeParent=1;resizeLast=0;collapsible=1;marginBottom=0;rounded=0;shadow=0;strokeWidth=1;" value="Predmet" vertex="1">
          <mxGeometry height="269" width="260" x="-130" y="611" as="geometry">
            <mxRectangle height="26" width="170" x="340" y="380" as="alternateBounds" />
          </mxGeometry>
        </mxCell>
        <mxCell id="1Qv8fr0okpyOL-LrenFo-24" parent="1Qv8fr0okpyOL-LrenFo-23" style="text;align=left;verticalAlign=top;spacingLeft=4;spacingRight=4;overflow=hidden;rotatable=0;points=[[0,0.5],[1,0.5]];portConstraint=eastwest;rounded=0;shadow=0;html=0;" value="-sifraPredmeta: int" vertex="1">
          <mxGeometry height="26" width="260" y="26" as="geometry" />
        </mxCell>
        <mxCell id="1Qv8fr0okpyOL-LrenFo-51" parent="1Qv8fr0okpyOL-LrenFo-23" style="text;align=left;verticalAlign=top;spacingLeft=4;spacingRight=4;overflow=hidden;rotatable=0;points=[[0,0.5],[1,0.5]];portConstraint=eastwest;rounded=0;shadow=0;html=0;" value="-studenti: List&lt;Student&gt;" vertex="1">
          <mxGeometry height="26" width="260" y="52" as="geometry" />
        </mxCell>
        <mxCell id="1Qv8fr0okpyOL-LrenFo-52" parent="1Qv8fr0okpyOL-LrenFo-23" style="text;align=left;verticalAlign=top;spacingLeft=4;spacingRight=4;overflow=hidden;rotatable=0;points=[[0,0.5],[1,0.5]];portConstraint=eastwest;rounded=0;shadow=0;html=0;" value="-sifraPredmeta: int" vertex="1">
          <mxGeometry height="26" width="260" y="78" as="geometry" />
        </mxCell>
        <mxCell id="QHBlkFtXS8DU_KKtdHjI-10" edge="1" parent="1Qv8fr0okpyOL-LrenFo-23" source="QHBlkFtXS8DU_KKtdHjI-9" style="endArrow=none;html=1;rounded=0;exitX=0;exitY=0;exitDx=0;exitDy=0;entryX=1;entryY=0;entryDx=0;entryDy=0;" target="QHBlkFtXS8DU_KKtdHjI-9" value="">
          <mxGeometry height="50" relative="1" width="50" as="geometry">
            <mxPoint x="40" y="169" as="sourcePoint" />
            <mxPoint x="90" y="119" as="targetPoint" />
          </mxGeometry>
        </mxCell>
        <mxCell id="QHBlkFtXS8DU_KKtdHjI-9" parent="1Qv8fr0okpyOL-LrenFo-23" style="text;html=1;whiteSpace=wrap;strokeColor=none;fillColor=none;align=left;verticalAlign=middle;rounded=0;" value="&lt;div&gt;&lt;br&gt;&lt;/div&gt;&lt;div&gt;&lt;br&gt;&lt;/div&gt;&lt;div&gt;&amp;lt;&amp;lt;create&amp;gt;&amp;gt; +Predmet(sifraPredmeta: int, )&lt;/div&gt;&lt;div&gt;&lt;br&gt;&lt;/div&gt;&lt;div&gt;+getSifraPredmeta()&lt;/div&gt;&lt;div&gt;&lt;br&gt;&lt;/div&gt;&lt;div&gt;+dodajStudenta(Student student)&lt;/div&gt;&lt;div&gt;&lt;br&gt;&lt;/div&gt;&lt;div&gt;+pregledajStudente() : List&amp;lt;Student&amp;gt;&lt;/div&gt;&lt;div&gt;&lt;span style=&quot;background-color: transparent; color: light-dark(rgb(0, 0, 0), rgb(255, 255, 255));&quot;&gt;&lt;br&gt;&lt;/span&gt;&lt;/div&gt;&lt;div&gt;&lt;span style=&quot;background-color: transparent; color: light-dark(rgb(0, 0, 0), rgb(255, 255, 255));&quot;&gt;+dodajZadacu(Zadaca zadaca)&lt;/span&gt;&lt;/div&gt;&lt;div&gt;&lt;br&gt;&lt;/div&gt;&lt;div&gt;+pregledajZadace() : List&amp;lt;Zadaca&amp;gt;&lt;/div&gt;" vertex="1">
          <mxGeometry height="140" width="260" y="104" as="geometry" />
        </mxCell>
        <mxCell id="1Qv8fr0okpyOL-LrenFo-25" parent="WIyWlLk6GJQsqaUBKTNV-1" style="swimlane;fontStyle=0;align=center;verticalAlign=top;childLayout=stackLayout;horizontal=1;startSize=26;horizontalStack=0;resizeParent=1;resizeLast=0;collapsible=1;marginBottom=0;rounded=0;shadow=0;strokeWidth=1;" value="Ispit" vertex="1">
          <mxGeometry height="250" width="250" x="-410" y="320" as="geometry">
            <mxRectangle height="26" width="170" x="340" y="380" as="alternateBounds" />
          </mxGeometry>
        </mxCell>
        <mxCell id="1Qv8fr0okpyOL-LrenFo-26" parent="1Qv8fr0okpyOL-LrenFo-25" style="text;align=left;verticalAlign=top;spacingLeft=4;spacingRight=4;overflow=hidden;rotatable=0;points=[[0,0.5],[1,0.5]];portConstraint=eastwest;rounded=0;shadow=0;html=0;" value="-id: int" vertex="1">
          <mxGeometry height="26" width="250" y="26" as="geometry" />
        </mxCell>
        <mxCell id="1Qv8fr0okpyOL-LrenFo-88" parent="1Qv8fr0okpyOL-LrenFo-25" style="text;align=left;verticalAlign=top;spacingLeft=4;spacingRight=4;overflow=hidden;rotatable=0;points=[[0,0.5],[1,0.5]];portConstraint=eastwest;rounded=0;shadow=0;html=0;" value="-datum: Date" vertex="1">
          <mxGeometry height="26" width="250" y="52" as="geometry" />
        </mxCell>
        <mxCell id="1Qv8fr0okpyOL-LrenFo-89" parent="1Qv8fr0okpyOL-LrenFo-25" style="text;align=left;verticalAlign=top;spacingLeft=4;spacingRight=4;overflow=hidden;rotatable=0;points=[[0,0.5],[1,0.5]];portConstraint=eastwest;rounded=0;shadow=0;html=0;" value="-rokZaPrijavu: Date" vertex="1">
          <mxGeometry height="26" width="250" y="78" as="geometry" />
        </mxCell>
        <mxCell id="1Qv8fr0okpyOL-LrenFo-90" parent="1Qv8fr0okpyOL-LrenFo-25" style="text;align=left;verticalAlign=top;spacingLeft=4;spacingRight=4;overflow=hidden;rotatable=0;points=[[0,0.5],[1,0.5]];portConstraint=eastwest;rounded=0;shadow=0;html=0;" value="-predmet: Predmet" vertex="1">
          <mxGeometry height="26" width="250" y="104" as="geometry" />
        </mxCell>
        <mxCell id="1Qv8fr0okpyOL-LrenFo-27" parent="WIyWlLk6GJQsqaUBKTNV-1" style="swimlane;fontStyle=0;align=center;verticalAlign=top;childLayout=stackLayout;horizontal=1;startSize=26;horizontalStack=0;resizeParent=1;resizeLast=0;collapsible=1;marginBottom=0;rounded=0;shadow=0;strokeWidth=1;" value="Zadaca" vertex="1">
          <mxGeometry height="143" width="160" x="-350" y="630.5" as="geometry">
            <mxRectangle height="26" width="170" x="340" y="380" as="alternateBounds" />
          </mxGeometry>
        </mxCell>
        <mxCell id="1Qv8fr0okpyOL-LrenFo-28" parent="1Qv8fr0okpyOL-LrenFo-27" style="text;align=left;verticalAlign=top;spacingLeft=4;spacingRight=4;overflow=hidden;rotatable=0;points=[[0,0.5],[1,0.5]];portConstraint=eastwest;rounded=0;shadow=0;html=0;" value="-nazivID: String " vertex="1">
          <mxGeometry height="26" width="160" y="26" as="geometry" />
        </mxCell>
        <mxCell id="1Qv8fr0okpyOL-LrenFo-64" parent="1Qv8fr0okpyOL-LrenFo-27" style="text;align=left;verticalAlign=top;spacingLeft=4;spacingRight=4;overflow=hidden;rotatable=0;points=[[0,0.5],[1,0.5]];portConstraint=eastwest;rounded=0;shadow=0;html=0;" value="-sifraPredmeta: int" vertex="1">
          <mxGeometry height="26" width="160" y="52" as="geometry" />
        </mxCell>
        <mxCell id="1Qv8fr0okpyOL-LrenFo-65" parent="1Qv8fr0okpyOL-LrenFo-27" style="text;align=left;verticalAlign=top;spacingLeft=4;spacingRight=4;overflow=hidden;rotatable=0;points=[[0,0.5],[1,0.5]];portConstraint=eastwest;rounded=0;shadow=0;html=0;" value="-rok: Date" vertex="1">
          <mxGeometry height="26" width="160" y="78" as="geometry" />
        </mxCell>
        <mxCell id="1Qv8fr0okpyOL-LrenFo-31" parent="WIyWlLk6GJQsqaUBKTNV-1" style="swimlane;fontStyle=0;align=center;verticalAlign=top;childLayout=stackLayout;horizontal=1;startSize=26;horizontalStack=0;resizeParent=1;resizeLast=0;collapsible=1;marginBottom=0;rounded=0;shadow=0;strokeWidth=1;" value="AdminZahtjev" vertex="1">
          <mxGeometry height="250" width="220" x="930" y="270" as="geometry">
            <mxRectangle height="26" width="170" x="340" y="380" as="alternateBounds" />
          </mxGeometry>
        </mxCell>
        <mxCell id="1Qv8fr0okpyOL-LrenFo-32" parent="1Qv8fr0okpyOL-LrenFo-31" style="text;align=left;verticalAlign=top;spacingLeft=4;spacingRight=4;overflow=hidden;rotatable=0;points=[[0,0.5],[1,0.5]];portConstraint=eastwest;rounded=0;shadow=0;html=0;" value="-id: int" vertex="1">
          <mxGeometry height="26" width="220" y="26" as="geometry" />
        </mxCell>
        <mxCell id="kA5UPvO6djHCNP10DwQC-10" parent="1Qv8fr0okpyOL-LrenFo-31" style="text;align=left;verticalAlign=top;spacingLeft=4;spacingRight=4;overflow=hidden;rotatable=0;points=[[0,0.5],[1,0.5]];portConstraint=eastwest;rounded=0;shadow=0;html=0;" value="-vrstaZahtjeva: enum" vertex="1">
          <mxGeometry height="26" width="220" y="52" as="geometry" />
        </mxCell>
        <mxCell id="kA5UPvO6djHCNP10DwQC-12" parent="1Qv8fr0okpyOL-LrenFo-31" style="text;align=left;verticalAlign=top;spacingLeft=4;spacingRight=4;overflow=hidden;rotatable=0;points=[[0,0.5],[1,0.5]];portConstraint=eastwest;rounded=0;shadow=0;html=0;" value="-obradjen: bool " vertex="1">
          <mxGeometry height="26" width="220" y="78" as="geometry" />
        </mxCell>
        <mxCell id="kA5UPvO6djHCNP10DwQC-13" parent="1Qv8fr0okpyOL-LrenFo-31" style="text;align=left;verticalAlign=top;spacingLeft=4;spacingRight=4;overflow=hidden;rotatable=0;points=[[0,0.5],[1,0.5]];portConstraint=eastwest;rounded=0;shadow=0;html=0;" value="-korisnik: Korisnik" vertex="1">
          <mxGeometry height="26" width="220" y="104" as="geometry" />
        </mxCell>
        <mxCell id="QHBlkFtXS8DU_KKtdHjI-22" parent="1Qv8fr0okpyOL-LrenFo-31" style="text;html=1;whiteSpace=wrap;strokeColor=none;fillColor=none;align=left;verticalAlign=middle;rounded=0;" value="&lt;div&gt;&amp;lt;&amp;lt;create&amp;gt;&amp;gt; +AdminZahtjev(id: int, vrstaZahtjeva: enum, korisnik Korisnik)&lt;/div&gt;&lt;div&gt;&lt;br&gt;&lt;/div&gt;&lt;div&gt;getVrstaZahtjeva()&lt;/div&gt;&lt;div&gt;&lt;br&gt;&lt;/div&gt;&lt;div&gt;getObradjen(), setObradjen(bool obradjen)&lt;/div&gt;&lt;div&gt;&lt;br&gt;&lt;/div&gt;" vertex="1">
          <mxGeometry height="120" width="220" y="130" as="geometry" />
        </mxCell>
        <mxCell id="QHBlkFtXS8DU_KKtdHjI-23" edge="1" parent="1Qv8fr0okpyOL-LrenFo-31" style="endArrow=none;html=1;rounded=0;entryX=1;entryY=0;entryDx=0;entryDy=0;" target="QHBlkFtXS8DU_KKtdHjI-22" value="">
          <mxGeometry height="50" relative="1" width="50" as="geometry">
            <mxPoint y="130" as="sourcePoint" />
            <mxPoint as="targetPoint" />
          </mxGeometry>
        </mxCell>
        <mxCell id="1Qv8fr0okpyOL-LrenFo-37" parent="WIyWlLk6GJQsqaUBKTNV-1" style="swimlane;fontStyle=0;align=center;verticalAlign=top;childLayout=stackLayout;horizontal=1;startSize=26;horizontalStack=0;resizeParent=1;resizeLast=0;collapsible=1;marginBottom=0;rounded=0;shadow=0;strokeWidth=1;" value="ProfesorPredmet" vertex="1">
          <mxGeometry height="110" width="170" x="210" y="830" as="geometry">
            <mxRectangle height="26" width="170" x="340" y="380" as="alternateBounds" />
          </mxGeometry>
        </mxCell>
        <mxCell id="1Qv8fr0okpyOL-LrenFo-38" parent="1Qv8fr0okpyOL-LrenFo-37" style="text;align=left;verticalAlign=top;spacingLeft=4;spacingRight=4;overflow=hidden;rotatable=0;points=[[0,0.5],[1,0.5]];portConstraint=eastwest;rounded=0;shadow=0;html=0;" value="-id: int" vertex="1">
          <mxGeometry height="26" width="170" y="26" as="geometry" />
        </mxCell>
        <mxCell id="1Qv8fr0okpyOL-LrenFo-39" parent="1Qv8fr0okpyOL-LrenFo-37" style="text;align=left;verticalAlign=top;spacingLeft=4;spacingRight=4;overflow=hidden;rotatable=0;points=[[0,0.5],[1,0.5]];portConstraint=eastwest;rounded=0;shadow=0;html=0;" value="-profesor: Profesor" vertex="1">
          <mxGeometry height="28" width="170" y="52" as="geometry" />
        </mxCell>
        <mxCell id="1Qv8fr0okpyOL-LrenFo-42" parent="1Qv8fr0okpyOL-LrenFo-37" style="text;align=left;verticalAlign=top;spacingLeft=4;spacingRight=4;overflow=hidden;rotatable=0;points=[[0,0.5],[1,0.5]];portConstraint=eastwest;rounded=0;shadow=0;html=0;" value="-predmet: Predmet" vertex="1">
          <mxGeometry height="26" width="170" y="80" as="geometry" />
        </mxCell>
        <mxCell id="1Qv8fr0okpyOL-LrenFo-43" edge="1" parent="WIyWlLk6GJQsqaUBKTNV-1" source="1Qv8fr0okpyOL-LrenFo-39" style="endArrow=open;html=1;endSize=12;startArrow=diamondThin;startSize=14;startFill=0;edgeStyle=orthogonalEdgeStyle;rounded=0;exitX=1;exitY=0.5;exitDx=0;exitDy=0;entryX=0.75;entryY=1;entryDx=0;entryDy=0;" target="zkfFHV4jXpPFQw0GAbJ--13" value="">
          <mxGeometry relative="1" as="geometry">
            <mxPoint x="510" y="680" as="sourcePoint" />
            <mxPoint x="590" y="580" as="targetPoint" />
          </mxGeometry>
        </mxCell>
        <mxCell id="1Qv8fr0okpyOL-LrenFo-44" connectable="0" parent="1Qv8fr0okpyOL-LrenFo-43" style="edgeLabel;resizable=0;html=1;align=left;verticalAlign=top;" value="1..n" vertex="1">
          <mxGeometry relative="1" x="-1" as="geometry" />
        </mxCell>
        <mxCell id="1Qv8fr0okpyOL-LrenFo-45" connectable="0" parent="1Qv8fr0okpyOL-LrenFo-43" style="edgeLabel;resizable=0;html=1;align=right;verticalAlign=top;" value="1" vertex="1">
          <mxGeometry relative="1" x="1" as="geometry">
            <mxPoint x="-8" y="11" as="offset" />
          </mxGeometry>
        </mxCell>
        <mxCell id="1Qv8fr0okpyOL-LrenFo-46" edge="1" parent="WIyWlLk6GJQsqaUBKTNV-1" source="1Qv8fr0okpyOL-LrenFo-39" style="endArrow=open;html=1;endSize=12;startArrow=diamondThin;startSize=14;startFill=0;edgeStyle=orthogonalEdgeStyle;rounded=0;exitX=0;exitY=0.5;exitDx=0;exitDy=0;entryX=1;entryY=0.5;entryDx=0;entryDy=0;" target="1Qv8fr0okpyOL-LrenFo-23" value="">
          <mxGeometry relative="1" as="geometry">
            <mxPoint x="5" y="585" as="sourcePoint" />
            <mxPoint x="165" y="585" as="targetPoint" />
          </mxGeometry>
        </mxCell>
        <mxCell id="1Qv8fr0okpyOL-LrenFo-48" connectable="0" parent="1Qv8fr0okpyOL-LrenFo-46" style="edgeLabel;resizable=0;html=1;align=right;verticalAlign=top;" value="1" vertex="1">
          <mxGeometry relative="1" x="1" as="geometry">
            <mxPoint x="20" y="-26" as="offset" />
          </mxGeometry>
        </mxCell>
        <mxCell id="1Qv8fr0okpyOL-LrenFo-50" connectable="0" parent="WIyWlLk6GJQsqaUBKTNV-1" style="edgeLabel;resizable=0;html=1;align=left;verticalAlign=top;" value="1..n" vertex="1">
          <mxGeometry x="190" y="870" as="geometry" />
        </mxCell>
        <mxCell id="1Qv8fr0okpyOL-LrenFo-61" edge="1" parent="WIyWlLk6GJQsqaUBKTNV-1" source="1Qv8fr0okpyOL-LrenFo-27" style="endArrow=open;endFill=1;endSize=12;html=1;rounded=0;entryX=0;entryY=0.5;entryDx=0;entryDy=0;exitX=1;exitY=0.5;exitDx=0;exitDy=0;" target="1Qv8fr0okpyOL-LrenFo-52" value="">
          <mxGeometry relative="1" width="160" as="geometry">
            <Array as="points" />
            <mxPoint x="-250" y="810" as="sourcePoint" />
            <mxPoint x="-90" y="810" as="targetPoint" />
          </mxGeometry>
        </mxCell>
        <mxCell id="1Qv8fr0okpyOL-LrenFo-62" connectable="0" parent="WIyWlLk6GJQsqaUBKTNV-1" style="edgeLabel;resizable=0;html=1;align=right;verticalAlign=top;" value="1" vertex="1">
          <mxGeometry x="-140" y="680" as="geometry" />
        </mxCell>
        <mxCell id="1Qv8fr0okpyOL-LrenFo-63" connectable="0" parent="WIyWlLk6GJQsqaUBKTNV-1" style="edgeLabel;resizable=0;html=1;align=right;verticalAlign=top;" value="0...*" vertex="1">
          <mxGeometry x="-170" y="680" as="geometry" />
        </mxCell>
        <mxCell id="1Qv8fr0okpyOL-LrenFo-67" parent="WIyWlLk6GJQsqaUBKTNV-1" style="swimlane;fontStyle=0;align=center;verticalAlign=top;childLayout=stackLayout;horizontal=1;startSize=26;horizontalStack=0;resizeParent=1;resizeLast=0;collapsible=1;marginBottom=0;rounded=0;shadow=0;strokeWidth=1;" value="PredajaZadace" vertex="1">
          <mxGeometry height="210" width="160" x="-380" y="80" as="geometry">
            <mxRectangle height="26" width="170" x="340" y="380" as="alternateBounds" />
          </mxGeometry>
        </mxCell>
        <mxCell id="1Qv8fr0okpyOL-LrenFo-68" parent="1Qv8fr0okpyOL-LrenFo-67" style="text;align=left;verticalAlign=top;spacingLeft=4;spacingRight=4;overflow=hidden;rotatable=0;points=[[0,0.5],[1,0.5]];portConstraint=eastwest;rounded=0;shadow=0;html=0;" value="-id: int" vertex="1">
          <mxGeometry height="26" width="160" y="26" as="geometry" />
        </mxCell>
        <mxCell id="1Qv8fr0okpyOL-LrenFo-69" parent="1Qv8fr0okpyOL-LrenFo-67" style="text;align=left;verticalAlign=top;spacingLeft=4;spacingRight=4;overflow=hidden;rotatable=0;points=[[0,0.5],[1,0.5]];portConstraint=eastwest;rounded=0;shadow=0;html=0;" value="-student: Student" vertex="1">
          <mxGeometry height="26" width="160" y="52" as="geometry" />
        </mxCell>
        <mxCell id="1Qv8fr0okpyOL-LrenFo-70" parent="1Qv8fr0okpyOL-LrenFo-67" style="text;align=left;verticalAlign=top;spacingLeft=4;spacingRight=4;overflow=hidden;rotatable=0;points=[[0,0.5],[1,0.5]];portConstraint=eastwest;rounded=0;shadow=0;html=0;" value="-zadaca: Zadaca" vertex="1">
          <mxGeometry height="26" width="160" y="78" as="geometry" />
        </mxCell>
        <mxCell id="1Qv8fr0okpyOL-LrenFo-71" parent="1Qv8fr0okpyOL-LrenFo-67" style="text;align=left;verticalAlign=top;spacingLeft=4;spacingRight=4;overflow=hidden;rotatable=0;points=[[0,0.5],[1,0.5]];portConstraint=eastwest;rounded=0;shadow=0;html=0;" value="-fajl: string" vertex="1">
          <mxGeometry height="26" width="160" y="104" as="geometry" />
        </mxCell>
        <mxCell id="1Qv8fr0okpyOL-LrenFo-73" parent="1Qv8fr0okpyOL-LrenFo-67" style="text;align=left;verticalAlign=top;spacingLeft=4;spacingRight=4;overflow=hidden;rotatable=0;points=[[0,0.5],[1,0.5]];portConstraint=eastwest;rounded=0;shadow=0;html=0;" value="-bodovi: int" vertex="1">
          <mxGeometry height="26" width="160" y="130" as="geometry" />
        </mxCell>
        <mxCell id="1Qv8fr0okpyOL-LrenFo-74" parent="1Qv8fr0okpyOL-LrenFo-67" style="text;align=left;verticalAlign=top;spacingLeft=4;spacingRight=4;overflow=hidden;rotatable=0;points=[[0,0.5],[1,0.5]];portConstraint=eastwest;rounded=0;shadow=0;html=0;" value="-status: enum" vertex="1">
          <mxGeometry height="26" width="160" y="156" as="geometry" />
        </mxCell>
        <mxCell id="1Qv8fr0okpyOL-LrenFo-76" parent="1Qv8fr0okpyOL-LrenFo-67" style="text;align=left;verticalAlign=top;spacingLeft=4;spacingRight=4;overflow=hidden;rotatable=0;points=[[0,0.5],[1,0.5]];portConstraint=eastwest;rounded=0;shadow=0;html=0;" value="-komentar: string" vertex="1">
          <mxGeometry height="26" width="160" y="182" as="geometry" />
        </mxCell>
        <mxCell id="1Qv8fr0okpyOL-LrenFo-77" edge="1" parent="WIyWlLk6GJQsqaUBKTNV-1" source="1Qv8fr0okpyOL-LrenFo-70" style="endArrow=open;html=1;endSize=12;startArrow=diamondThin;startSize=14;startFill=0;edgeStyle=orthogonalEdgeStyle;rounded=0;exitX=1;exitY=0.5;exitDx=0;exitDy=0;entryX=0;entryY=0.75;entryDx=0;entryDy=0;" target="zkfFHV4jXpPFQw0GAbJ--6" value="">
          <mxGeometry relative="1" as="geometry">
            <mxPoint x="-86.5" y="366" as="sourcePoint" />
            <mxPoint x="-53.5" y="240" as="targetPoint" />
          </mxGeometry>
        </mxCell>
        <mxCell id="1Qv8fr0okpyOL-LrenFo-78" connectable="0" parent="1Qv8fr0okpyOL-LrenFo-77" style="edgeLabel;resizable=0;html=1;align=left;verticalAlign=top;" value="1..n" vertex="1">
          <mxGeometry relative="1" x="-1" as="geometry" />
        </mxCell>
        <mxCell id="1Qv8fr0okpyOL-LrenFo-79" connectable="0" parent="1Qv8fr0okpyOL-LrenFo-77" style="edgeLabel;resizable=0;html=1;align=right;verticalAlign=top;" value="1" vertex="1">
          <mxGeometry relative="1" x="1" as="geometry">
            <mxPoint x="-8" y="11" as="offset" />
          </mxGeometry>
        </mxCell>
        <mxCell id="1Qv8fr0okpyOL-LrenFo-80" edge="1" parent="WIyWlLk6GJQsqaUBKTNV-1" source="1Qv8fr0okpyOL-LrenFo-74" style="endArrow=open;html=1;endSize=12;startArrow=diamondThin;startSize=14;startFill=0;edgeStyle=orthogonalEdgeStyle;rounded=0;exitX=0;exitY=0.5;exitDx=0;exitDy=0;entryX=0;entryY=0.5;entryDx=0;entryDy=0;" target="1Qv8fr0okpyOL-LrenFo-28" value="">
          <mxGeometry relative="1" as="geometry">
            <Array as="points">
              <mxPoint x="-430" y="479" />
              <mxPoint x="-430" y="670" />
              <mxPoint x="-370" y="670" />
            </Array>
            <mxPoint x="-450" y="606" as="sourcePoint" />
            <mxPoint x="-417" y="480" as="targetPoint" />
          </mxGeometry>
        </mxCell>
        <mxCell id="1Qv8fr0okpyOL-LrenFo-81" connectable="0" parent="1Qv8fr0okpyOL-LrenFo-80" style="edgeLabel;resizable=0;html=1;align=left;verticalAlign=top;" value="1..n" vertex="1">
          <mxGeometry relative="1" x="-1" as="geometry">
            <mxPoint x="-30" as="offset" />
          </mxGeometry>
        </mxCell>
        <mxCell id="1Qv8fr0okpyOL-LrenFo-82" connectable="0" parent="1Qv8fr0okpyOL-LrenFo-80" style="edgeLabel;resizable=0;html=1;align=right;verticalAlign=top;" value="1" vertex="1">
          <mxGeometry relative="1" x="1" as="geometry">
            <mxPoint x="-8" y="11" as="offset" />
          </mxGeometry>
        </mxCell>
        <mxCell id="1Qv8fr0okpyOL-LrenFo-83" parent="WIyWlLk6GJQsqaUBKTNV-1" style="swimlane;fontStyle=0;align=center;verticalAlign=top;childLayout=stackLayout;horizontal=1;startSize=26;horizontalStack=0;resizeParent=1;resizeLast=0;collapsible=1;marginBottom=0;rounded=0;shadow=0;strokeWidth=1;" value="PrijavaIspit" vertex="1">
          <mxGeometry height="280" width="220" x="-60" y="200" as="geometry">
            <mxRectangle height="26" width="170" x="340" y="380" as="alternateBounds" />
          </mxGeometry>
        </mxCell>
        <mxCell id="1Qv8fr0okpyOL-LrenFo-84" parent="1Qv8fr0okpyOL-LrenFo-83" style="text;align=left;verticalAlign=top;spacingLeft=4;spacingRight=4;overflow=hidden;rotatable=0;points=[[0,0.5],[1,0.5]];portConstraint=eastwest;rounded=0;shadow=0;html=0;" value="-id: int" vertex="1">
          <mxGeometry height="26" width="220" y="26" as="geometry" />
        </mxCell>
        <mxCell id="1Qv8fr0okpyOL-LrenFo-85" parent="1Qv8fr0okpyOL-LrenFo-83" style="text;align=left;verticalAlign=top;spacingLeft=4;spacingRight=4;overflow=hidden;rotatable=0;points=[[0,0.5],[1,0.5]];portConstraint=eastwest;rounded=0;shadow=0;html=0;" value="-student: Student" vertex="1">
          <mxGeometry height="26" width="220" y="52" as="geometry" />
        </mxCell>
        <mxCell id="1Qv8fr0okpyOL-LrenFo-86" parent="1Qv8fr0okpyOL-LrenFo-83" style="text;align=left;verticalAlign=top;spacingLeft=4;spacingRight=4;overflow=hidden;rotatable=0;points=[[0,0.5],[1,0.5]];portConstraint=eastwest;rounded=0;shadow=0;html=0;" value="-ispit: Ispit" vertex="1">
          <mxGeometry height="26" width="220" y="78" as="geometry" />
        </mxCell>
        <mxCell id="1Qv8fr0okpyOL-LrenFo-87" parent="1Qv8fr0okpyOL-LrenFo-83" style="text;align=left;verticalAlign=top;spacingLeft=4;spacingRight=4;overflow=hidden;rotatable=0;points=[[0,0.5],[1,0.5]];portConstraint=eastwest;rounded=0;shadow=0;html=0;" value="-status: enum" vertex="1">
          <mxGeometry height="26" width="220" y="104" as="geometry" />
        </mxCell>
        <mxCell id="QHBlkFtXS8DU_KKtdHjI-13" parent="1Qv8fr0okpyOL-LrenFo-83" style="text;html=1;whiteSpace=wrap;strokeColor=none;fillColor=none;align=left;verticalAlign=middle;rounded=0;" value="&lt;div&gt;&lt;br&gt;&lt;/div&gt;&lt;div&gt;&amp;lt;&amp;lt;create&amp;gt;&amp;gt; +PrijavaIspit(id: int, student:&amp;nbsp;&lt;/div&gt;&lt;div&gt;Student, ispit: Ispit, status: enum status&lt;/div&gt;&lt;div&gt;&lt;br&gt;&lt;/div&gt;&lt;div&gt;+getStatus()&lt;/div&gt;&lt;div&gt;&lt;br&gt;&lt;/div&gt;&lt;div&gt;+setStatus(enum status): enum status&lt;/div&gt;&lt;div&gt;&lt;br&gt;&lt;/div&gt;&lt;div&gt;+potvrdiPrijavu()&lt;/div&gt;&lt;div&gt;&lt;br&gt;&lt;/div&gt;&lt;div&gt;+otkaziPrijavu()&lt;/div&gt;&lt;div style=&quot;&quot;&gt;&lt;br&gt;&lt;/div&gt;" vertex="1">
          <mxGeometry height="150" width="220" y="130" as="geometry" />
        </mxCell>
        <mxCell id="QHBlkFtXS8DU_KKtdHjI-14" edge="1" parent="1Qv8fr0okpyOL-LrenFo-83" source="QHBlkFtXS8DU_KKtdHjI-13" style="endArrow=none;html=1;rounded=0;exitX=0;exitY=0;exitDx=0;exitDy=0;entryX=1;entryY=0;entryDx=0;entryDy=0;" target="QHBlkFtXS8DU_KKtdHjI-13" value="">
          <mxGeometry height="50" relative="1" width="50" as="geometry">
            <mxPoint x="40" y="190" as="sourcePoint" />
            <mxPoint x="90" y="140" as="targetPoint" />
          </mxGeometry>
        </mxCell>
        <mxCell id="1Qv8fr0okpyOL-LrenFo-94" edge="1" parent="WIyWlLk6GJQsqaUBKTNV-1" source="1Qv8fr0okpyOL-LrenFo-83" style="endArrow=open;html=1;endSize=12;startArrow=diamondThin;startSize=14;startFill=0;edgeStyle=orthogonalEdgeStyle;rounded=0;exitX=0.5;exitY=0;exitDx=0;exitDy=0;entryX=0.5;entryY=1;entryDx=0;entryDy=0;" target="zkfFHV4jXpPFQw0GAbJ--6" value="">
          <mxGeometry relative="1" as="geometry">
            <mxPoint x="-40" y="523" as="sourcePoint" />
            <mxPoint x="150" y="500" as="targetPoint" />
          </mxGeometry>
        </mxCell>
        <mxCell id="1Qv8fr0okpyOL-LrenFo-95" connectable="0" parent="1Qv8fr0okpyOL-LrenFo-94" style="edgeLabel;resizable=0;html=1;align=left;verticalAlign=top;" value="1..n" vertex="1">
          <mxGeometry relative="1" x="-1" as="geometry">
            <mxPoint x="10" y="-30" as="offset" />
          </mxGeometry>
        </mxCell>
        <mxCell id="1Qv8fr0okpyOL-LrenFo-96" connectable="0" parent="1Qv8fr0okpyOL-LrenFo-94" style="edgeLabel;resizable=0;html=1;align=right;verticalAlign=top;" value="1" vertex="1">
          <mxGeometry relative="1" x="1" as="geometry">
            <mxPoint x="-8" y="11" as="offset" />
          </mxGeometry>
        </mxCell>
        <mxCell id="1Qv8fr0okpyOL-LrenFo-97" edge="1" parent="WIyWlLk6GJQsqaUBKTNV-1" source="1Qv8fr0okpyOL-LrenFo-83" style="endArrow=open;html=1;endSize=12;startArrow=diamondThin;startSize=14;startFill=0;edgeStyle=orthogonalEdgeStyle;rounded=0;exitX=0.5;exitY=1;exitDx=0;exitDy=0;entryX=1;entryY=0.5;entryDx=0;entryDy=0;" target="1Qv8fr0okpyOL-LrenFo-88" value="">
          <mxGeometry relative="1" as="geometry">
            <mxPoint x="10" y="543" as="sourcePoint" />
            <mxPoint x="200" y="520" as="targetPoint" />
          </mxGeometry>
        </mxCell>
        <mxCell id="1Qv8fr0okpyOL-LrenFo-98" connectable="0" parent="1Qv8fr0okpyOL-LrenFo-97" style="edgeLabel;resizable=0;html=1;align=left;verticalAlign=top;" value="1..n" vertex="1">
          <mxGeometry relative="1" x="-1" as="geometry">
            <mxPoint y="10" as="offset" />
          </mxGeometry>
        </mxCell>
        <mxCell id="1Qv8fr0okpyOL-LrenFo-99" connectable="0" parent="1Qv8fr0okpyOL-LrenFo-97" style="edgeLabel;resizable=0;html=1;align=right;verticalAlign=top;" value="1" vertex="1">
          <mxGeometry relative="1" x="1" as="geometry">
            <mxPoint x="30" y="-5" as="offset" />
          </mxGeometry>
        </mxCell>
        <mxCell id="1Qv8fr0okpyOL-LrenFo-100" edge="1" parent="WIyWlLk6GJQsqaUBKTNV-1" source="1Qv8fr0okpyOL-LrenFo-23" style="endArrow=open;endFill=1;endSize=12;html=1;rounded=0;entryX=1;entryY=0.5;entryDx=0;entryDy=0;exitX=0.25;exitY=0;exitDx=0;exitDy=0;" target="1Qv8fr0okpyOL-LrenFo-90" value="">
          <mxGeometry relative="1" width="160" as="geometry">
            <Array as="points">
              <mxPoint x="-90" y="600" />
            </Array>
            <mxPoint x="-40" y="550" as="sourcePoint" />
            <mxPoint x="100" y="550" as="targetPoint" />
          </mxGeometry>
        </mxCell>
        <mxCell id="1Qv8fr0okpyOL-LrenFo-101" connectable="0" parent="WIyWlLk6GJQsqaUBKTNV-1" style="edgeLabel;resizable=0;html=1;align=right;verticalAlign=top;" value="0...*" vertex="1">
          <mxGeometry x="-60" y="585" as="geometry" />
        </mxCell>
        <mxCell id="1Qv8fr0okpyOL-LrenFo-102" connectable="0" parent="WIyWlLk6GJQsqaUBKTNV-1" style="edgeLabel;resizable=0;html=1;align=right;verticalAlign=top;" value="1" vertex="1">
          <mxGeometry x="-140" y="440" as="geometry" />
        </mxCell>
        <mxCell id="kA5UPvO6djHCNP10DwQC-0" parent="WIyWlLk6GJQsqaUBKTNV-1" style="swimlane;fontStyle=0;align=center;verticalAlign=top;childLayout=stackLayout;horizontal=1;startSize=26;horizontalStack=0;resizeParent=1;resizeLast=0;collapsible=1;marginBottom=0;rounded=0;shadow=0;strokeWidth=1;" value="ZahtjevZaDokument&#xa;" vertex="1">
          <mxGeometry height="270" width="240" x="270" y="-261" as="geometry">
            <mxRectangle height="26" width="170" x="340" y="380" as="alternateBounds" />
          </mxGeometry>
        </mxCell>
        <mxCell id="kA5UPvO6djHCNP10DwQC-1" parent="kA5UPvO6djHCNP10DwQC-0" style="text;align=left;verticalAlign=top;spacingLeft=4;spacingRight=4;overflow=hidden;rotatable=0;points=[[0,0.5],[1,0.5]];portConstraint=eastwest;rounded=0;shadow=0;html=0;" value="-id: int" vertex="1">
          <mxGeometry height="26" width="240" y="26" as="geometry" />
        </mxCell>
        <mxCell id="kA5UPvO6djHCNP10DwQC-2" parent="kA5UPvO6djHCNP10DwQC-0" style="text;align=left;verticalAlign=top;spacingLeft=4;spacingRight=4;overflow=hidden;rotatable=0;points=[[0,0.5],[1,0.5]];portConstraint=eastwest;rounded=0;shadow=0;html=0;" value="-tipDokumenta: enum" vertex="1">
          <mxGeometry height="26" width="240" y="52" as="geometry" />
        </mxCell>
        <mxCell id="kA5UPvO6djHCNP10DwQC-3" parent="kA5UPvO6djHCNP10DwQC-0" style="text;align=left;verticalAlign=top;spacingLeft=4;spacingRight=4;overflow=hidden;rotatable=0;points=[[0,0.5],[1,0.5]];portConstraint=eastwest;rounded=0;shadow=0;html=0;" value="-student: Student" vertex="1">
          <mxGeometry height="26" width="240" y="78" as="geometry" />
        </mxCell>
        <mxCell id="kA5UPvO6djHCNP10DwQC-4" parent="kA5UPvO6djHCNP10DwQC-0" style="text;align=left;verticalAlign=top;spacingLeft=4;spacingRight=4;overflow=hidden;rotatable=0;points=[[0,0.5],[1,0.5]];portConstraint=eastwest;rounded=0;shadow=0;html=0;" value="-status: bool" vertex="1">
          <mxGeometry height="26" width="240" y="104" as="geometry" />
        </mxCell>
        <mxCell id="kA5UPvO6djHCNP10DwQC-5" edge="1" parent="WIyWlLk6GJQsqaUBKTNV-1" source="zkfFHV4jXpPFQw0GAbJ--6" style="endArrow=block;endFill=1;html=1;edgeStyle=orthogonalEdgeStyle;align=left;verticalAlign=top;rounded=0;exitX=0.5;exitY=0;exitDx=0;exitDy=0;entryX=0;entryY=0.5;entryDx=0;entryDy=0;" target="kA5UPvO6djHCNP10DwQC-2" value="0...*">
          <mxGeometry relative="1" x="0.8384" y="25" as="geometry">
            <mxPoint as="offset" />
            <Array as="points">
              <mxPoint y="-220" />
              <mxPoint x="85" y="-220" />
              <mxPoint x="85" y="-196" />
            </Array>
            <mxPoint x="-40" y="10" as="sourcePoint" />
            <mxPoint x="200" y="-150" as="targetPoint" />
          </mxGeometry>
        </mxCell>
        <mxCell id="kA5UPvO6djHCNP10DwQC-6" connectable="0" parent="kA5UPvO6djHCNP10DwQC-5" style="edgeLabel;resizable=0;html=1;align=left;verticalAlign=bottom;" value="1" vertex="1">
          <mxGeometry relative="1" x="-1" as="geometry" />
        </mxCell>
        <mxCell id="kA5UPvO6djHCNP10DwQC-7" edge="1" parent="WIyWlLk6GJQsqaUBKTNV-1" source="1Qv8fr0okpyOL-LrenFo-22" style="endArrow=diamondThin;endFill=0;endSize=24;html=1;rounded=0;entryX=1;entryY=0.5;entryDx=0;entryDy=0;exitX=0;exitY=0.5;exitDx=0;exitDy=0;edgeStyle=orthogonalEdgeStyle;" target="kA5UPvO6djHCNP10DwQC-1" value="">
          <mxGeometry relative="1" width="160" as="geometry">
            <mxPoint x="1159.2800000000002" y="129.19000000000005" as="sourcePoint" />
            <mxPoint x="827" y="-199.99999999999977" as="targetPoint" />
          </mxGeometry>
        </mxCell>
        <mxCell id="kA5UPvO6djHCNP10DwQC-14" edge="1" parent="WIyWlLk6GJQsqaUBKTNV-1" source="1Qv8fr0okpyOL-LrenFo-4" style="endArrow=diamondThin;endFill=0;endSize=24;html=1;rounded=0;exitX=1;exitY=0.5;exitDx=0;exitDy=0;edgeStyle=orthogonalEdgeStyle;entryX=0;entryY=0.5;entryDx=0;entryDy=0;" target="kA5UPvO6djHCNP10DwQC-12" value="">
          <mxGeometry relative="1" width="160" as="geometry">
            <mxPoint x="1091" y="1020" as="sourcePoint" />
            <mxPoint x="940" y="500" as="targetPoint" />
          </mxGeometry>
        </mxCell>
        <mxCell id="kA5UPvO6djHCNP10DwQC-16" edge="1" parent="WIyWlLk6GJQsqaUBKTNV-1" source="1Qv8fr0okpyOL-LrenFo-11" style="endArrow=block;endFill=1;html=1;edgeStyle=orthogonalEdgeStyle;align=left;verticalAlign=top;rounded=0;exitX=1;exitY=0.5;exitDx=0;exitDy=0;entryX=0.25;entryY=0;entryDx=0;entryDy=0;" target="1Qv8fr0okpyOL-LrenFo-31" value="0...*">
          <mxGeometry relative="1" x="0.842" y="30" as="geometry">
            <mxPoint as="offset" />
            <Array as="points">
              <mxPoint x="580" y="170" />
              <mxPoint x="985" y="170" />
            </Array>
            <mxPoint x="720" y="305" as="sourcePoint" />
            <mxPoint x="944" y="170" as="targetPoint" />
          </mxGeometry>
        </mxCell>
        <mxCell id="kA5UPvO6djHCNP10DwQC-17" connectable="0" parent="kA5UPvO6djHCNP10DwQC-16" style="edgeLabel;resizable=0;html=1;align=left;verticalAlign=bottom;" value="1" vertex="1">
          <mxGeometry relative="1" x="-1" as="geometry" />
        </mxCell>
        <mxCell id="QHBlkFtXS8DU_KKtdHjI-11" parent="WIyWlLk6GJQsqaUBKTNV-1" style="text;html=1;whiteSpace=wrap;strokeColor=none;fillColor=none;align=left;verticalAlign=middle;rounded=0;" value="&lt;div&gt;&amp;lt;&amp;lt;create&amp;gt;&amp;gt; +Ispit(id: int, datum: Date, rokZaPrijavu: Date, predmet: Predmet)&lt;/div&gt;&lt;div&gt;&lt;span style=&quot;background-color: transparent; color: light-dark(rgb(0, 0, 0), rgb(255, 255, 255));&quot;&gt;+getDatum()&lt;/span&gt;&lt;/div&gt;&lt;div&gt;&lt;span style=&quot;background-color: transparent; color: light-dark(rgb(0, 0, 0), rgb(255, 255, 255));&quot;&gt;+setDatum(Date datum)&amp;nbsp;&lt;/span&gt;&lt;/div&gt;&lt;div&gt;+getRokZaPrijavu() +setRokZaPrijavu(Date rok)&lt;/div&gt;&lt;div&gt;+dodajPrijavu(PrijavaIspit prijava)&lt;/div&gt;&lt;div&gt;+provjeriRokZaPrijavu() : bool&lt;/div&gt;" vertex="1">
          <mxGeometry height="120" width="250" x="-410" y="450" as="geometry" />
        </mxCell>
        <mxCell id="QHBlkFtXS8DU_KKtdHjI-12" edge="1" parent="WIyWlLk6GJQsqaUBKTNV-1" source="QHBlkFtXS8DU_KKtdHjI-11" style="endArrow=none;html=1;rounded=0;exitX=0;exitY=0;exitDx=0;exitDy=0;entryX=1;entryY=0;entryDx=0;entryDy=0;" target="QHBlkFtXS8DU_KKtdHjI-11" value="">
          <mxGeometry height="50" relative="1" width="50" as="geometry">
            <mxPoint x="-150" y="580" as="sourcePoint" />
            <mxPoint x="-100" y="530" as="targetPoint" />
          </mxGeometry>
        </mxCell>
        <mxCell id="QHBlkFtXS8DU_KKtdHjI-15" parent="WIyWlLk6GJQsqaUBKTNV-1" style="text;html=1;whiteSpace=wrap;strokeColor=none;fillColor=none;align=left;verticalAlign=middle;rounded=0;" value="&lt;div&gt;&amp;lt;&amp;lt;create&amp;gt;&amp;gt; +ZahtjevZaDokument(id: int, tipDokumenta: enum, student: Student, status: bool)&lt;/div&gt;&lt;div&gt;&lt;br&gt;&lt;/div&gt;&lt;div&gt;+getTipDokumenta()&lt;/div&gt;&lt;div&gt;&lt;br&gt;&lt;/div&gt;&lt;div&gt;+getStatus(), setStatus(bool status)&lt;/div&gt;&lt;div&gt;&lt;br&gt;&lt;/div&gt;&lt;div&gt;+obradiZahtjev()&lt;/div&gt;&lt;div&gt;&lt;br&gt;&lt;/div&gt;" vertex="1">
          <mxGeometry height="150" width="240" x="270" y="-130" as="geometry" />
        </mxCell>
        <mxCell id="QHBlkFtXS8DU_KKtdHjI-16" edge="1" parent="WIyWlLk6GJQsqaUBKTNV-1" source="QHBlkFtXS8DU_KKtdHjI-15" style="endArrow=none;html=1;rounded=0;exitX=0;exitY=0;exitDx=0;exitDy=0;entryX=1;entryY=0;entryDx=0;entryDy=0;" target="QHBlkFtXS8DU_KKtdHjI-15" value="">
          <mxGeometry height="50" relative="1" width="50" as="geometry">
            <mxPoint x="420" y="-70" as="sourcePoint" />
            <mxPoint x="460" y="-110" as="targetPoint" />
          </mxGeometry>
        </mxCell>
      </root>
    </mxGraphModel>
  </diagram>
</mxfile>
